flexai/__init__.py
flexai/agent.py
flexai/cli.py
flexai/client.py
flexai/config.py
flexai/executor.py
flexai/project.py
flexai/utils.py
flexai_agent-0.1.0.dist-info/licenses/LICENSE
tests/__init__.py
tests/test_agent.py
tests/test_client.py
flexai_agent-0.1.0.dist-info/METADATA
flexai_agent-0.1.0.dist-info/WHEEL
flexai_agent-0.1.0.dist-info/entry_points.txt
flexai_agent-0.1.0.dist-info/top_level.txt
flexai_agent-0.1.0.dist-info/RECORD
