Metadata-Version: 2.4
Name: flexai-agent
Version: 0.1.0
Summary: API-agnostic agentic Python package with configurable providers
Home-page: https://github.com/kelleyblackmore/Flexai
Author: Kelley Blackmore
Author-email: Kelley Blackmore <kelleyblackmore@gmail.com>
Maintainer-email: Kelley Blackmore <kelleyblackmore@gmail.com>
License: MIT
Project-URL: Homepage, https://github.com/kelleyblackmore/Flexai
Project-URL: Documentation, https://github.com/kelleyblackmore/Flexai/tree/main/docs
Project-URL: Repository, https://github.com/kelleyblackmore/Flexai
Project-URL: Issues, https://github.com/kelleyblackmore/Flexai/issues
Project-URL: Changelog, https://github.com/kelleyblackmore/Flexai/blob/main/UPDATES.md
Keywords: ai,agent,openai,llm,code-generation,chat,automation
Classifier: Development Status :: 4 - Beta
Classifier: Intended Audience :: Developers
Classifier: Operating System :: OS Independent
Classifier: Programming Language :: Python :: 3
Classifier: Programming Language :: Python :: 3.11
Classifier: Programming Language :: Python :: 3.12
Classifier: Programming Language :: Python :: 3.13
Classifier: Topic :: Software Development :: Libraries :: Python Modules
Classifier: Topic :: Software Development :: Code Generators
Classifier: Topic :: Scientific/Engineering :: Artificial Intelligence
Requires-Python: >=3.11
Requires-Dist: click>=8.2.1
Requires-Dist: openai>=1.97.0
Requires-Dist: pyyaml>=6.0.2
Requires-Dist: requests>=2.32.4
Requires-Dist: rich>=14.0.0
Dynamic: author
Dynamic: home-page
Dynamic: requires-python
